cleansort/__init__.py
cleansort/api.py
cleansort/database_handler.py
cleansort/metadata_cleaner.py
cleansort/metadata_sorter.py
tests/__init__.py
tests/test_cleansort.py
cleansort-0.1.0.dist-info/METADATA
cleansort-0.1.0.dist-info/WHEEL
cleansort-0.1.0.dist-info/top_level.txt
cleansort-0.1.0.dist-info/RECORD
