Metadata-Version: 2.1
Name: cleansort
Version: 0.1.0
Summary: A library for cleaning and sorting metadata
Home-page: https://github.com/yourusername/cleansort
Author: Your Name
Author-email: Your Name <your.email@example.com>
Project-URL: Homepage, https://github.com/yourusername/cleansort
Project-URL: Bug Tracker, https://github.com/yourusername/cleansort/issues
Classifier: Programming Language :: Python :: 3
Classifier: License :: OSI Approved :: MIT License
Classifier: Operating System :: OS Independent
Requires-Python: >=3.7
Requires-Dist: pandas>=1.5.0
Requires-Dist: sqlalchemy>=2.0.0
Requires-Dist: beautifulsoup4>=4.9.3
Requires-Dist: flask>=3.0.0
